mediawiki_mcp_server/main.py
mseep_mediawiki_mcp_server-0.0.2.dist-info/METADATA
mseep_mediawiki_mcp_server-0.0.2.dist-info/WHEEL
mseep_mediawiki_mcp_server-0.0.2.dist-info/entry_points.txt
mseep_mediawiki_mcp_server-0.0.2.dist-info/RECORD
