Metadata-Version: 2.4
Name: mseep-mediawiki-mcp-server
Version: 0.0.2
Summary: A MCP server for MediaWiki
Author-email: mseep <support@skydeck.ai>
Requires-Python: >=3.13
Requires-Dist: httpx<0.28
Requires-Dist: loguru>=0.7.3
Requires-Dist: mcp[cli,ws]>=1.11.0
